{
    "KPlugin": {
        "Authors": [
            {
                "Email": "philip.falkner@gmail.com, mgraesslin@kde.org",
                "Name": "Philip Falkner, Martin Gräßlin"
            }
        ],
        "Category": "Window Open/Close Animation",
        "Description": "Make windows smoothly fade in and out when they are shown or hidden",
        "EnabledByDefault": false,
        "Icon": "preferences-system-windows-effect-fade",
        "Id": "kwin4_effect_fade",
        "License": "GPL",
        "Name": "Fade",
        "ServiceTypes": [
            "KWin/Effect"
        ],
        "Version": "0.2.0"
    },
    "X-KDE-Ordering": "60",
    "X-KWin-Exclusive-Category": "toplevel-open-close-animation",
    "X-Plasma-API": "javascript",
    "X-Plasma-MainScript": "code/main.js"
}
