{
    "KPlugin": {
        "Category": "Virtual Desktop Switching Animation",
        "Description": "Slide desktops when switching virtual desktops",
        "Description[ar]": "مرر أسطح المكتب عند التبديل الأسطح الافتراضية",
        "Description[az]": "Virtual İş Masalarını dəyişərkən iş masalarını sürüşdürür",
        "Description[be]": "Ссоўване працоўных сталоў пры пераключэнні віртуальных працоўных сталоў",
        "Description[bg]": "Плъзгане настрани на работните плотове при превключване на виртуални работни плотове",
        "Description[ca@valencia]": "Llisca els escriptoris en canviar els escriptoris virtuals",
        "Description[ca]": "Llisca els escriptoris en canviar els escriptoris virtuals",
        "Description[cs]": "Klouzat plochami při přepínání virtuálních ploch",
        "Description[de]": "Lässt Fenster beim Wechsel von virtuellen Arbeitsflächen über den Bildschirm gleiten",
        "Description[en_GB]": "Slide desktops when switching virtual desktops",
        "Description[es]": "Deslizar los escritorios al cambiar de escritorio virtual",
        "Description[et]": "Töölaudade liuglemine virtuaalsete töölaudade vahel liikumisel",
        "Description[eu]": "Irristatu mahaigainak alegiazko mahaigaina aldatzean",
        "Description[fi]": "Liu’uta työpöytiä virtuaalityöpöytää vaihdettaessa",
        "Description[fr]": "Faire glisser les bureaux lors du basculement des bureaux virtuels",
        "Description[gl]": "Esvarar os escritorios ao cambiar de escritorio virtual.",
        "Description[hu]": "Asztalok csúsztatása a virtuális asztalok közötti váltáskor",
        "Description[ia]": "Glissa scriptorios quando on commuta scriptorios virtual",
        "Description[id]": "Geser desktop ketika beralih virtual desktop",
        "Description[it]": "Fai scorrere i desktop quando cambi i desktop virtuali",
        "Description[ja]": "仮想デスクトップを切り替えるときデスクトップをスライドします",
        "Description[ka]": "სამუშაო მაგიდების გასრიალება ვირტუალური სამუშაო მაგიდების გადართვისას",
        "Description[ko]": "가상 바탕 화면간을 전환할 때 슬라이딩 효과를 사용합니다",
        "Description[nl]": "Schuift vensters tijdens het wisselen van virtuele bureaubladen",
        "Description[nn]": "La skriveborda skli bortover skjermen ved veksling mellom skrivebord",
        "Description[pl]": "Przesuwa pulpity wirtualne przy przełączaniu",
        "Description[pt]": "Deslizar os ecrãs ao mudar de ecrãs virtuais",
        "Description[pt_BR]": "Desliza as áreas de trabalho ao trocar entre as áreas de trabalho virtuais",
        "Description[ro]": "Alunecă birourile la schimbarea biroului virtual",
        "Description[ru]": "Эффект прокрутки при переходе на другой рабочий стол",
        "Description[sk]": "Kľzať plochy pri prepínaní virtuálnych plôch",
        "Description[sl]": "Podrsa namizja ob preklapljanju med navideznimi omizji",
        "Description[sv]": "Låt skrivbord skjutas vid byte av virtuella skrivbord",
        "Description[tr]": "Sanal masaüstleri değiştirilirken masaüstlerini kaydır",
        "Description[uk]": "Ковзання стільниць під час час перемикання стільниць",
        "Description[vi]": "Trượt qua các bàn làm việc khi chuyển bàn làm việc ảo",
        "Description[x-test]": "xxSlide desktops when switching virtual desktopsxx",
        "Description[zh_CN]": "虚拟桌面切换时呈现滑动动效",
        "Description[zh_TW]": "在虛擬桌面間切換時使用滑動效果",
        "EnabledByDefault": true,
        "Id": "slide",
        "License": "GPL",
        "Name": "Slide",
        "Name[ar]": "أزْلِق",
        "Name[az]": "Slayd",
        "Name[be]": "Ссоўванне",
        "Name[bg]": "Плъзгане",
        "Name[ca@valencia]": "Lliscament",
        "Name[ca]": "Lliscament",
        "Name[cs]": "Sklouznutí",
        "Name[de]": "Gleiten",
        "Name[en_GB]": "Slide",
        "Name[es]": "Deslizar",
        "Name[et]": "Liuglemine",
        "Name[eu]": "Irristatu",
        "Name[fi]": "Työpöytäliuku",
        "Name[fr]": "Diapositive",
        "Name[gl]": "Esvarar",
        "Name[hu]": "Csúsztatott váltás",
        "Name[ia]": "Glissa",
        "Name[id]": "Slide",
        "Name[it]": "Scivola",
        "Name[ja]": "スライド",
        "Name[ka]": "სლაიდი",
        "Name[ko]": "슬라이드",
        "Name[nl]": "Dia",
        "Name[nn]": "Skliding",
        "Name[pl]": "Slajd",
        "Name[pt]": "Deslizar",
        "Name[pt_BR]": "Deslizar",
        "Name[ro]": "Alunecă",
        "Name[ru]": "Скольжение",
        "Name[sk]": "Posúvať",
        "Name[sl]": "Drsaj",
        "Name[sv]": "Skjut",
        "Name[tr]": "Kaydır",
        "Name[uk]": "Ковзання",
        "Name[vi]": "Trượt",
        "Name[x-test]": "xxSlidexx",
        "Name[zh_CN]": "滑动",
        "Name[zh_TW]": "滑動"
    },
    "X-KDE-ConfigModule": "kwin_slide_config",
    "org.kde.kwin.effect": {
        "exclusiveGroup": "desktop-animations",
        "video": "https://files.kde.org/plasma/kwin/effect-videos/slide.ogv"
    }
}
