{
    "KPlugin": {
        "Category": "Appearance",
        "Description": "Helper effect for screenshot tools",
        "Description[ar]": "تأثير مساعدة لأدوات التقاط الشاشة",
        "Description[az]": "Ekranın şəklini çəkən vasitə üçün köməkçi effekt",
        "Description[be]": "Дапаможны эфект для інструментаў для стварэння здымкаў экрана",
        "Description[bg]": "Помощен ефект за инструменти за снимка на екрана",
        "Description[ca@valencia]": "Efecte auxiliar per a les eines de captura de pantalla",
        "Description[ca]": "Efecte auxiliar per a les eines de captura de pantalla",
        "Description[cs]": "Pomocný efekt pro nástroje snímku obrazovky",
        "Description[de]": "Hilfseffekt für Bildschirmfotos",
        "Description[en_GB]": "Helper effect for screenshot tools",
        "Description[es]": "Efecto auxiliar para las herramientas de captura de pantalla",
        "Description[et]": "Ekraanipildi tegemise tööriistade abiefekt",
        "Description[eu]": "Pantaila-argazki tresnentzako efektu laguntzailea",
        "Description[fi]": "Ruutukaappaustyökalujen avustustehoste",
        "Description[fr]": "Effet d'assistance pour les outils de copie d'écran",
        "Description[gl]": "Efecto auxiliar para ferramentas de captura de pantalla.",
        "Description[hu]": "Segédeffektus a képernyőkép-készítő eszközökhöz",
        "Description[ia]": "Effecto adjutante pro instrumentos de instantanee de schermo",
        "Description[id]": "Efek penunjang untuk peralatan skrinsut",
        "Description[it]": "Effetto di assistenza per strumenti di schermate",
        "Description[ja]": "スクリーンショットツールのためのヘルパー効果",
        "Description[ka]": "ეკრანის ანაბეჭდის ხელსაწყოების დამხმარე ეფექტი",
        "Description[ko]": "스크린샷 도구 도우미 효과",
        "Description[nl]": "Effect van hulp voor hulpmiddelen bij schermafdruk",
        "Description[nn]": "Hjelpareffekt for skjermbiletverktøy",
        "Description[pl]": "Efekt pomocniczy dla zrzutów ekranu",
        "Description[pt]": "Efeito auxiliar para as ferramentas de captura do ecrã",
        "Description[pt_BR]": "Efeito auxiliar para ferramentas de captura de tela",
        "Description[ro]": "Efect ajutător pentru unelte de capturare a ecranului",
        "Description[ru]": "Вспомогательный эффект для инструментов создания снимков экрана",
        "Description[sk]": "Pomocný efekt pre nástroje snímky obrazovky",
        "Description[sl]": "Učinki pomočnika za orodja posnetka zaslona",
        "Description[sv]": "Hjälpeffekt för skärmbildsverktyg",
        "Description[ta]": "திரைப்பிடிப்புகளை எடுக்க உதவும் அசைவூட்டம்",
        "Description[tr]": "Ekran görüntüsü araçları için yardımcı etkisi",
        "Description[uk]": "Допоміжний ефект для створення знімків екрана",
        "Description[vi]": "Hiệu ứng trợ giúp cho các công cụ chụp ảnh màn hình",
        "Description[x-test]": "xxHelper effect for screenshot toolsxx",
        "Description[zh_CN]": "屏幕截图工具的辅助效果",
        "Description[zh_TW]": "螢幕快照工具輔助效果",
        "EnabledByDefault": true,
        "Id": "screenshot",
        "License": "GPL",
        "Name": "Screenshot",
        "Name[ar]": "لقطة شاشة",
        "Name[az]": "Ekran şəklini çəkmək",
        "Name[be]": "Здымак экрана",
        "Name[bg]": "Екранна снимка",
        "Name[ca@valencia]": "Captura de pantalla",
        "Name[ca]": "Captura de pantalla",
        "Name[cs]": "Snímek obrazovky",
        "Name[de]": "Bildschirmfoto",
        "Name[en_GB]": "Screenshot",
        "Name[es]": "Captura de pantalla",
        "Name[et]": "Ekraanipilt",
        "Name[eu]": "Pantaila-argazkia",
        "Name[fi]": "Ruutukaappaus",
        "Name[fr]": "Copie d'écran",
        "Name[gl]": "Captura de pantalla",
        "Name[hu]": "Képernyőkép",
        "Name[ia]": "Captura de schermo",
        "Name[id]": "Screenshot",
        "Name[it]": "Schermata",
        "Name[ja]": "スクリーンショット",
        "Name[ka]": "ეკრანის ანაბეჭდი",
        "Name[ko]": "스크린샷",
        "Name[nl]": "Schermafdruk",
        "Name[nn]": "Skjermbilete",
        "Name[pl]": "Zrzut ekranu",
        "Name[pt]": "Captura",
        "Name[pt_BR]": "Captura de tela",
        "Name[ro]": "Captură de ecran",
        "Name[ru]": "Снимок экрана",
        "Name[sk]": "Snímka obrazovky",
        "Name[sl]": "Posnetek zaslona",
        "Name[sv]": "Skärmbild",
        "Name[ta]": "திரைப்பிடிப்பு",
        "Name[tr]": "Ekran Görüntüsü",
        "Name[uk]": "Знімок вікна",
        "Name[vi]": "Ảnh chụp màn hình",
        "Name[x-test]": "xxScreenshotxx",
        "Name[zh_CN]": "屏幕截图",
        "Name[zh_TW]": "螢幕快照"
    },
    "org.kde.kwin.effect": {
        "internal": true
    }
}
